typedlist/__init__.py
typedlist/typedlist.py
typedlist-0.0.1.dist-info/METADATA
typedlist-0.0.1.dist-info/WHEEL
typedlist-0.0.1.dist-info/top_level.txt
typedlist-0.0.1.dist-info/RECORD
